setup.py
dist_pack/Binomialdistribution.py
dist_pack/Gaussiandistribution.py
dist_pack/Generaldistribution.py
dist_pack/__init__.py
dist_pack.egg-info/PKG-INFO
dist_pack.egg-info/SOURCES.txt
dist_pack.egg-info/dependency_links.txt
dist_pack.egg-info/not-zip-safe
dist_pack.egg-info/top_level.txt