Metadata-Version: 1.0
Name: dist-pack
Version: 0.2
Summary: Gaussian and binomial distributions
Home-page: UNKNOWN
Author: Fernando de la Torre
Author-email: fernandodelatorre4@gmail.com
License: UNKNOWN
Platform: UNKNOWN
